listme/__init__.py
listme/_main.py
listme/config.py
listme/git_tools.py
listme/parser.py
listme-0.2.dist-info/LICENSE
listme-0.2.dist-info/METADATA
listme-0.2.dist-info/WHEEL
listme-0.2.dist-info/entry_points.txt
listme-0.2.dist-info/top_level.txt
listme-0.2.dist-info/RECORD
