Metadata-Version: 2.1
Name: listme
Version: 0.2
Summary: Summarize you FIXME, TODO, XXX (and other tags) comments so you don't forget them.
Author-email: Matheus Pedroni <pnmatheus@protonmail.com>
License: GNU GENERAL PUBLIC LICENSE
Classifier: Programming Language :: Python :: 3
Classifier: License :: OSI Approved :: GNU General Public License v3 (GPLv3)
Classifier: Operating System :: Unix
Requires-Python: >=3.8
License-File: LICENSE
Requires-Dist: rich (>=12.6.0)
Requires-Dist: platformdirs (>=2.6.0)
